{
  "version": "7",
  "dialect": "postgresql",
  "entries": [
    {
      "idx": 0,
      "version": "7",
      "when": 1782743597033,
      "tag": "0000_exotic_karnak",
      "breakpoints": true
    },
    {
      "idx": 1,
      "version": "7",
      "when": 1782816244111,
      "tag": "0001_dry_slipstream",
      "breakpoints": true
    },
    {
      "idx": 2,
      "version": "7",
      "when": 1782834864751,
      "tag": "0002_crazy_dreadnoughts",
      "breakpoints": true
    },
    {
      "idx": 3,
      "version": "7",
      "when": 1782868367531,
      "tag": "0003_add_account_id_indexes",
      "breakpoints": true
    }
  ]
}